<!DOCTYPE verb SYSTEM "verb.dtd">
<verb>
    <id> 交手 </id>
    <frameset id="f1">
        <role argnum="0" argrole="agent"/>
        <role argnum="1" argrole="co-arg0"/>
        <frame>
            <mapping>
                <V/>
                <mapitem src="sbj" trg="arg0"/>
            </mapping>
            <example>
                <parse>
                    费拉拉 和 现在 的 波尔多主帅 劳伦特布兰克 赛季 在 那不勒斯 曾经 并肩 作战 ， 后者 效力 国际 米兰 的 时候 也 多 次 和 费拉拉 #交手#
                </parse>
                <arg n="0">后者</arg>
                <arg n="1">
                    费拉拉
                </arg>
                <V/>
            </example>
        </frame>
    </frameset>
</verb>
