<!DOCTYPE verb SYSTEM "verb.dtd">
<verb>
    <id> 常设 </id>
    <frameset id="f1">
        <role argnum="0" argrole="agent"/>
        <role argnum="1" argrole="theme"/>
        <role argnum="2" argrole="locative"/>
        <frame>
            <mapping>
                <V/>
                <mapitem src="sbj" trg="arg0"/>
            </mapping>
            <example>
                <parse>
                    印度 媒体 的 报道 说 ， 目前 ， 印度 国防部 拒绝 就 阿尼 空军 基地 事 发表 任何 评论 ， 但 有 高级 官员 私下 透露 说 ， 印军 在 中亚 #常设# 军事 基地 完全 是 出于 在 中亚 地区 长远 的 战略 需求 ， 来 可以 保证 印度 能 接触 中亚 ， 二 来 也 可以 保证 印度 能源 需求 的 安全 
                </parse>
                <arg n="0">
                    印军
                </arg>
                <arg n="1">军事 基地</arg>
                <arg n="2">中亚</arg>
                <V/>
            </example>
        </frame>
    </frameset>
</verb>
