<!DOCTYPE verb SYSTEM "verb.dtd">
<verb>
    <id> 惠存 </id>
    <frameset id="f1">
        <role argnum="0" argrole="agent"/>
        <role argnum="1" argrole="theme"/>
        <frame>
            <mapping>
                <V/>
                <mapitem src="sbj" trg="arg0"/>
            </mapping>
            <example>
                <parse>
                    在 这 块 表的 盖 子 上 刻有 金荣 夫子 大人 #惠存# ， 蒋 中正 敬赠 字样
                </parse>
                <arg n="0">
                    金荣 夫子 大人
                </arg>
                <V/>
            </example>
        </frame>
    </frameset>
</verb>
