<!DOCTYPE verb SYSTEM "verb.dtd">
<verb>
    <id> 惹火 </id>
    <frameset id="f1">
        <role argnum="0" argrole="agent"/>
        <role argnum="1" argrole="theme"/>
        <frame>
            <mapping>
                <V/>
                <mapitem src="sbj" trg="arg0"/>
            </mapping>
            <example>
                <parse>
                    可是 有 次 她 真的 把 我 #惹火# 了 ， 我 狠 狠 的 训了 她 一顿 
                </parse>
                <arg n="0">
                    她
                </arg>
                <arg n="1">
                    我
                </arg>
                <V/>
            </example>
        </frame>
    </frameset>
    <frameset id="f2">
        <role argnum="0" argrole="entity with the property"/>
        <frame>
            <mapping>
                <V/>
                <mapitem src="sbj" trg="arg0"/>
            </mapping>
            <example>
                <parse>
                    朱茵 娇嫩 粉色 比基尼 让 朱茵 散发 女性 魅力 ， 姣好 身材性感 #惹火#
                </parse>
                <arg n="0">
                    姣好 身材
                </arg>
                <V/>
            </example>
        </frame>
    </frameset>
    <frameset id="f3">
        <role argnum="0" argrole="agent"/>
        <frame>
            <mapping>
                <V/>
                <mapitem src="sbj" trg="arg0"/>
            </mapping>
            <example>
                <parse>
                    当然 我 宁 肯 相信 它 是 恶 搞 ， 是 诽谤 从 红楼 选 秀宝钗 组进 比赛 中 被 淘汰 出局 的 徐行 ， 一个年 仅 18 岁 的 姑娘 ， #惹火# 烧身 了
                </parse>
                <arg n="0">
                    一个年 仅 18 岁 的 姑娘
                </arg>
                <V/>
            </example>
        </frame>
    </frameset>
</verb>
