<!DOCTYPE verb SYSTEM "verb.dtd">
<verb>
    <id> 戗 </id>
    <frameset id="f1">
        <role argnum="0" argrole="agent"/>
        <role argnum="1" argrole="theme"/>
        <frame>
            <mapping>
                <V/>
                <mapitem src="sbj" trg="arg0"/>
            </mapping>
            <example>
                <parse>
                    本人 承接 以下 业务 苦力 搬运 ， 车工 ， 瓦工 ， 砸墙 ， 砌墙 ， 通下 水道 ， 办证 ， 暗杀 ， 洗 钱 ， 要 债 ， 割双 眼皮 抢 小孩 棒棒糖 ， 复仇 十 岁 以下 业务 ， 扶老 太太 过 马路 ， 擦皮 鞋 ， 修理 雨伞 ， 磨 剪子 ， #戗# 菜刀 
                </parse>
                <arg n="1">
                    菜刀 
                </arg>
                <V/>
            </example>
        </frame>
    </frameset>
</verb>
