<!DOCTYPE verb SYSTEM "verb.dtd">
<verb>
    <id> 抖擞 </id>
    <frameset id="f1">
        <role argnum="0" argrole="agent"/>
        <role argnum="1" argrole="theme"/>
        <frame>
            <mapping>
                <V/>
                <mapitem src="sbj" trg="arg0"/>
            </mapping>
            <example>
                <parse>
                    全 场 嘘声四起 ， 这时候 林丹 才 #抖擞# 精神 ， 连续 追 了 几 个 球 
                </parse>
                <arg n="0">
                    林丹
                </arg>
                <arg n="1">精神</arg>
                <V/>
            </example>
        </frame>
    </frameset>
    <frameset id="f2">
        <role argnum="0" argrole="entity with the property"/>
        <frame>
            <mapping>
                <V/>
                <mapitem src="sbj" trg="arg0"/>
            </mapping>
            <example>
                <parse>
                    只一件 衬衣一件 夹克 ， 在 上海 冬天 的 街头 ， 他 静静 的 默默无闻 的 站着 ， 但是 很 #抖擞# 
                </parse>
                <arg n="0">
                    他
                </arg>
                <V/>
            </example>
        </frame>
    </frameset>
    <frameset id="f3">
        <role argnum="0" argrole="agent"/>
        <role argnum="1" argrole="theme"/>
        <frame>
            <mapping>
                <V/>
                <mapitem src="sbj" trg="arg0"/>
            </mapping>
            <example>
                <parse>
                    姐姐 倒 了 盆热水 ， 最后 给 父亲 洗 了 洗脸 ， 妈妈 #抖擞# 着 双 手 在 堂屋 门口放 上 只 水碗 ， 再 摆上 根 筷子 ， 父亲 出发 了 ， 顾及 不 了 家 老小 的 泪水
                </parse>
                <arg n="0">
                    妈妈
                </arg>
                <arg n="1">双 手</arg>
                <V/>
            </example>
        </frame>
    </frameset>
</verb>
