<!DOCTYPE verb SYSTEM "verb.dtd">
<verb>
    <id> 挣来 </id>
    <frameset id="f1">
        <role argnum="0" argrole=""/>
        <frame>
            <mapping>
                <V/>
                <mapitem src="sbj" trg="arg0"/>
            </mapping>
            <example>
                <parse>
                    ( (IP (NP-SBJ (CP (WHNP-1 (-NONE- *OP*)) 
                    (CP (IP (IP-SBJ (NP-PN-SBJ (NR 中国))
                    (VP (VV 崛起)))
                    (PU ，)
                    (VP (VV 靠)
                    (NP-OBJ (-NONE- *T*-1))))
                    (DEC 的))))
                    (VP (VC 是)
                    (CP-PRD (IP (NP-SBJ (NN 中国人))
                    (VP (PP-MNR (P 用)
                    (NP (NN 双手)
                    (CC 和)
                    (NN 智慧)))
                    (NP-MNR (NP (QP (CD 一)
                    (CLP (M 分)))
                    (NP (NN 钱)))
                    (NP (QP (CD 一)
                    (CLP (M 分)))
                    (NP (NN 钱))))
                    (VP (VV 挣来))))
                    (SP 的)))
                    (PU 。))) 
                </parse>
                <arg n="0">中国人</arg>
                <arg n="m" f="MNR">(PP-MNR (P 用)
                    (NP (NN 双手)
                    (CC 和)
                    (NN 智慧))
                </arg>
                <arg n="m" f="MNR">(NP-MNR (NP (QP (CD 一)
                    (CLP (M 分)))
                    (NP (NN 钱)))
                    (NP (QP (CD 一)
                    (CLP (M 分)))
                    (NP (NN 钱))))
                </arg>
                <V/>
            </example>
        </frame>
    </frameset>
</verb>
