<!DOCTYPE verb SYSTEM "verb.dtd">
<verb>
    <id> 来缘于 </id>
    <frameset id="f1">
        <role argnum="0" argrole="entity"/>
        <role argnum="1" argrole="source"/>
        <frame>
            <mapping>
                <V/>
                <mapitem src="sbj" trg="arg0"/>
            </mapping>
            <example>
                <parse>
                    ( (IP (PU ：)
                    (CD 02)
                    (VP (ADVP (AD 不))
                    (VP (VV 起)))
                    (DEC 的)
                    (PU 。)
                    (IP (NP-SBJ (NN 幸福))
                    (VP (VC 是)
                    (NP-PRD (QP (CD 一)
                    (CLP (M 种)))
                    (NP (NN 感觉)))))
                    (PU ，)
                    (IP (NP-SBJ (DNP (NP (DNP (NP (NN 国外))
                    (DEG 的))
                    (NP (NN 中国人)))
                    (DEG 的))
                    (NP (NN 幸福感)))
                    (VP (VV 来缘于)
                    (VP (PP (P 和)
                    (NP (DNP (NP (NN 国内))
                    (DEG 的))
                    (NP (NN 中国人))))
                    (VP (VV 比较)))))
                    (PU 。)
                    (IP (NP-SBJ (-NONE- *pro*)) 
                    (VP (ADVP (AD 最))
                    (VP (ADVP (AD 常))
                    (VP (VV 见))))))) 
                </parse>
                <arg n="0">(NP-SBJ (DNP (NP (DNP (NP (NN 国外))
                    (DEG 的))
                    (NP (NN 中国人)))
                    (DEG 的))
                    (NP (NN 幸福感)))
                </arg>
                <arg n="1">(VP (PP (P 和)
                    (NP (DNP (NP (NN 国内))
                    (DEG 的))
                    (NP (NN 中国人))))
                    (VP (VV 比较))))
                </arg>
                <V/>
            </example>
        </frame>
    </frameset>
</verb>
