<!DOCTYPE verb SYSTEM "verb.dtd">
<verb>
    <id> 稍加 </id>
    <frameset id="f1">
        <role argnum="0" argrole="agent"/>
        <role argnum="1" argrole="action"/>
        <frame>
            <mapping>
                <V/>
                <mapitem src="sbj" trg="arg0"/>
            </mapping>
            <example>
                <parse>
                    ( (IP (ADVP (AD 其实))
                    (CP-CND (ADVP (CS 只要))
                    (IP (NP-SBJ (-NONE- *pro*))
                    (VP (PP-DIR (P 对)
                    (NP (DNP (NP (NP-PN (NR 中共))
                    (NP (NN 高层)))
                    (DEG 的))
                    (NP (NN 决策)
                    (NN 过程))))
                    (VP (VV 稍加)
                    (NP-OBJ (NN 了解))))))
                    (PU ，)
                    (NP-SBJ (-NONE- *pro*))
                    (VP (ADVP (AD 就))
                    (VP (VV 会)
                    (VP (VV 想到)
                    (PU ，)
                    (IP-OBJ (PP-TMP (P 在)
                    (LCP (NP (NP (IP (IP (NP-SBJ (NN 地震))
                    (VP (VV 发生)))
                    (CC 到)
                    (IP (NP-SBJ (-NONE- *pro*))
                    (VP (VV 公布)
                    (NP-OBJ (NN 消息)))))
                    (NP (NN 中间)))
                    (DNP (NP (DP (DT 这)
                    (QP (QP (CD 半)
                    (CLP (M 个)))
                    (ADVP (CD 多))))
                    (NP (NN 小时)))
                    (DEG 的))
                    (NP (NN 时间)))
                    (LC 里)))
                    (PU ，)
                    (NP-SBJ (NP-PN (NR 中共))
                    (NP (NN 政治局)
                    (NN 常委会)))
                    (VP (VP (ADVP (AD 绝不))
                    (VP (VC 是)
                    (VP (ADVP (AD 在))
                    (VP (VV 核实)
                    (NP-OBJ (DNP (NP (NN 震级))
                    (DEG 的))
                    (NP (NN 准确度)))))))
                    (PU ，)
                    (VP (ADVP (AD 而))
                    (VP (VC 是)
                    (VP (PP-TMP (P 在)
                    (LCP (IP (NP-SBJ (-NONE- *pro*)) 
                    (VP (VV 收集)
                    (AS 了)
                    (NP-OBJ (DNP (QP (ADVP (AD 尽可能))
                    (QP (CD 多)))
                    (DEG 的))
                    (ADJP (JJ 第一手))
                    (NP (NN 情报)))))
                    (LC 后)))
                    (PU ，)
                    (DVP (VP (VA 艰难))
                    (DEV 地))
                    (VP (VV 进行)
                    (AS 着)
                    (NP-OBJ (NN 政治)
                    (NN 抉择)))))))))))
                    (PU 。))) 
                </parse>
                <arg n="m" f="ADV">其实</arg>
                <arg n="m" f="DIS">只要</arg>
                <arg n="0">*pro*</arg>
                <arg n="1">了解</arg>
                <V/>
            </example>
        </frame>
    </frameset>
</verb>
