<!DOCTYPE verb SYSTEM "verb.dtd">
<verb>
    <id> 企稳 </id>
    <frameset id="f1">
        <role argnum="0" argrole="entity that is stable, usually price"/>
        <frame>
            <mapping>
                <V/>
                <mapitem src="sbj" trg="arg0"/>
            </mapping>
            <example>
                <parse>
                    ( (IP (ADVP-ADV (AD 而且))
                    (PU ，)
                    (PP-MNR (P 随着)
                    (IP (NP-SBJ (DNP (NP (NP-APP (NN 猪肉)
                    (ETC 等))
                    (NP (QP (CD 一些))
                    (ADJP (JJ 关键))
                    (NP (NN 商品))))
                    (DEG 的))
                    (NP (NN 价格)))
                    (VP (VA 企稳))))
                    (PU ，)
                    (NP-SBJ (ADJP (JJ 总体))
                    (NP (NN 通货膨胀率)))
                    (VP (PP-TMP (P 在)
                    (NP (NP (NT 未来))
                    (QP (CD 几)
                    (CLP (M 个)))
                    (NP (NN 月))))
                    (ADVP (AD 将))
                    (ADVP (AD 进一步))
                    (VP (VV 下降)))
                    (PU 。))) 
                </parse>
                <arg n="0">(NP-SBJ (DNP (NP (NP-APP (NN 猪肉)
                    (ETC 等))
                    (NP (QP (CD 一些))
                    (ADJP (JJ 关键))
                    (NP (NN 商品))))
                    (DEG 的))
                    (NP (NN 价格)))
                </arg>
                <V/>
            </example>
        </frame>
    </frameset>
</verb>
