<!DOCTYPE verb SYSTEM "verb.dtd">
<verb>
    <id> 不敬 </id>
    <frameset id="f1">
        <role argnum="0" argrole="agent or entity"/>
        <role argnum="1" argrole="object that Arg0 lacks of respect to"/>
        <frame>
            <mapping>
                <V/>
                <mapitem src="sbj" trg="arg0"/>
            </mapping>
            <example>
                <parse>
                    ( (IP-HLN (NP-SBJ (QP (CD 一)
                    (CLP (M 个)))
                    (CP (WHNP-1 (-NONE- *OP*))
                    (CP (IP (NP-SBJ (-NONE- *T*-1))
                    (VP (ADVP (AD 终身))
                    (VP (VV 当)
                    (NP-OBJ (NN 领导))
                    (PP (ADVP (AD 直))
                    (PP (P 到)
                    (IP (NP-SBJ (-NONE- *PRO*)) 
                    (VP (VV 死亡))))))))
                    (DEC 的)))
                    (NP (NN 知识)
                    (NN 分子)))
                    (PU －－)
                    (VP (VV 说)
                    (NP-OBJ (QP (CD 几)
                    (CLP (M 句)))
                    (CP (WHNP-2 (-NONE- *OP*))
                    (CP (IP (NP-SBJ (-NONE- *T*-2))
                    (VP (PP (P 对)
                    (NP-PN (NR 巴)
                    (NN 主任)))
                    (VP (VA 不敬))))
                    (DEC 的)))
                    (NP (NN 话)))))) 
                </parse>
                <arg n="0">话*T*-2 </arg>
                <arg n="1">(PP (P 对)
                    (NP-PN (NR 巴)
                    (NN 主任)))
                </arg>
                <V/>
            </example>
        </frame>
    </frameset>
</verb>
