<!DOCTYPE verb SYSTEM "verb.dtd">
<verb>
    <id> 息肩 </id>
    <frameset id="f1">
        <role argnum="0" argrole="agent"/>
        <frame>
            <mapping>
                <V/>
                <mapitem src="sbj" trg="arg0"/>
            </mapping>
            <example>
                <parse>
                    ( (IP (NP-SBJ (NP-APP (QP (CD ８２)
                    (CLP (M 岁)))
                    (NP (NN 老人)))
                    (NP-PN (NR 陈振应)))
                    (VP (ADVP (AD 含泪))
                    (VP (VV 赋诗)
                    (PU ：)
                    (PU “)
                    (IP-OBJ (NP-SBJ (-NONE- *pro*))
                    (VP (VP (VP (PP-BNF (P 为)
                    (NP (NN 民)))
                    (VP (VV 辛劳)))
                    (VP (ADVP (AD 未))
                    (VP (VV 息肩))))
                    (PU ，)
                    (VP (VP (VV 高烧)
                    (QP-EXT (CD 四)
                    (CLP (M 日))))
                    (VP (ADVP (AD 仍))
                    (VP (VV 向前))))))))
                    (PU 。))) 
                </parse>
                <arg n="0">*pro*</arg>
                <arg n="m" f="BNF">(PP-BNF (P 为)
                    (NP (NN 民))
                </arg>
                <arg n="m" f="ADV">未</arg>
                
                <V/>
            </example>
        </frame>
    </frameset>
</verb>
