<!DOCTYPE verb SYSTEM "verb.dtd">
<verb>
    <id> 供暖 </id>
    <frameset id="f1">
        <role argnum="0" argrole="provider"/>
        <frame>
            <mapping>
                <V/>
                <mapitem src="sbj" trg="arg0"/>
            </mapping>
            <example>
                <parse>
                    ( (IP (FLR (IJ 呃))
                    (PU ，)
                    (NP-SBJ-2 (CP (WHNP-1 (-NONE- *OP*))
                    (CP (IP (NP-SBJ (-NONE- *T*-1))
                    (VP (VV 供暖)))
                    (DEC 的)))
                    (NP (NN 管线)))
                    (FLR (SP 呢))
                    (VP (ADVP (AD 确实))
                    (ADVP (AD 已经))
                    (VP (SB 被)
                    (VP (VV 破坏)
                    (AS 了)
                    (NP-OBJ (-NONE- *-2)))))
                    (PU ，))) 
                    
                </parse>
                <arg n="m" f="MNR">
                    *T*-1 
                </arg>
                <V/>
            </example>
        </frame>
    </frameset>
</verb>
