<!DOCTYPE verb SYSTEM "verb.dtd">
<verb>
    <id> 电熟 </id>
    <frameset id="f1">
        <role argnum="0" argrole="agent or cause"/>
        <role argnum="1" argrole="entity that is cooked by electricity "/>
        <frame>
            <mapping>
                <V/>
                <mapitem src="sbj" trg="arg0"/>
                <mapitem src="npobj" trg="arg1"/>
            </mapping>
            <example>
                <parse>
                    ( (IP (IP (NP-SBJ (NN 腿))
                    (VP (ADVP (AD 一样))
                    (VP (VC 是)
                    (NP-PRD (NN 电伤)))))
                    (PU ，)
                    (CP (IP (DFL (NN 电))
                    (NP-SBJ (-NONE- *pro*))
                    (VP (VV 电熟)
                    (NP-OBJ (NN 皮))))
                    (SP 了))
                    (PU 。))) 
                    
                </parse>
                <arg n="0">
                    
                </arg>
                <arg n="1">
                    皮
                </arg>
                <V/>
            </example>
        </frame>
    </frameset>
</verb>
