<!DOCTYPE verb SYSTEM "verb.dtd">
<verb>
    <id> 白流 </id>
    <frameset id="f1">
        <role argnum="0" argrole="sweat or blood"/>
        <frame>
            <mapping>
                <V/>
                <mapitem src="sbj" trg="arg0"/>
            </mapping>
            <example>
                <parse>
                    ( (IP (NP-SBJ (ADJP (JJ 科学))
                    (NP (NN 发展观)))
                    (VP (ADVP (AD 绝对))
                    (ADVP (AD 不))
                    (VP (VV 会)
                    (VP (VP (ADVP (AD 随便))
                    (VP (VV 浪费)))
                    (PU ，)
                    (VP (ADVP (AD 随便))
                    (VP (VV 让)
                    (NP-OBJ (DNP (NP (NN 人民))
                    (DEG 的))
                    (NP (NN 血汗)))
                    (IP (NP-SBJ (-NONE- *PRO*))
                    (VP (VV 白流))))))))
                    (PU ，))) 
                    
                </parse>
                <arg n="0">
                    *PRO*
                </arg>
                <V/>
            </example>
        </frame>
    </frameset>
</verb>
