<!DOCTYPE verb SYSTEM "verb.dtd">
<verb>
    <id> 厮混 </id>
    <frameset id="f1">
        <role argnum="0" argrole="agent"/>
        <role argnum="1" argrole="theme or co-arg0"/>
        <role argnum="2" argrole="locative"/>
        <frame>
            <mapping>
                <V/>
                <mapitem src="sbj" trg="arg0"/>
            </mapping>
            <example>
                <parse>
                    一个 清华 大学 的 高材生 ， 要 成天 与 这样 一些 人 打交道 ， 与 这样 一些 人 #厮混# 在一起 ， 让 这样 些 人 认可 自己 ， 并 不 是 件 容易 的 事 ， 需要 撕去 伪装 ， 真正 与 群众 打成 片
                </parse>
                <arg n="0">
                    一个 清华 大学 的 高材生
                </arg>
                <arg n="1">这样 一些 人</arg>
                <V/>
            </example>
        </frame>
        <frame>
            <mapping>
                <V/>
                <mapitem src="sbj" trg="arg0"/>
            </mapping>
            <example>
                <parse>
                    年轻 时髦 的 他 成为 社交圈 的 红 人 ，与 一等 人 #厮混# 于 巴黎 最 有名 的 夜总 会 
                </parse>
                <arg n="0">
                    年轻 时髦 的 他
                </arg>
                <arg n="1">一等 人</arg>
                <arg n="2">巴黎 最 有名 的 夜总 会</arg>
                <V/>
            </example>
        </frame>
    </frameset>
</verb>
