<!DOCTYPE verb SYSTEM "verb.dtd">
<verb>
    <id> 唱票 </id>
    <frameset id="f1">
        <role argnum="0" argrole="agent"/>
        <frame>
            <mapping>
                <V/>
                <mapitem src="sbj" trg="arg0"/>
            </mapping>
            <example>
                <parse>
                    中国 青年报 记者 在 时代 庄园 社区 居委会 换届 选举 现场 看到 ， 有 两 人 #唱票# ， 两 人 监票 ， 监票 的 两 人 中 一人 是 派出 所 的 民警 
                </parse>
                <arg n="0">
                    两 人
                </arg>
                <V/>
            </example>
        </frame>
    </frameset>
</verb>
