<!DOCTYPE verb SYSTEM "verb.dtd">
<verb>
    <id> 嗔怪 </id>
    <frameset id="f1">
        <role argnum="0" argrole="agent"/>
        <role argnum="1" argrole="theme"/>
        <role argnum="2" argrole="content"/>
        <frame>
            <mapping>
                <V/>
                <mapitem src="sbj" trg="arg0"/>
            </mapping>
            <example>
                <parse>
                    没 想到 大家 的 反应 都 很 支持 ， 也 非常 欣赏 ， 没有 人 支持 她 退赛 ， 同 寝室 的 姐妹 #嗔怪# 她 都 什么 年代 了 ， 还 这么 保守 
                </parse>
                <arg n="0">
                    同 寝室 的 姐妹
                </arg>
                <arg n="1">她</arg>
                <arg n="2">都 什么 年代 了 ， 还 这么 保守</arg>
                <V/>
            </example>
        </frame>
    </frameset>
</verb>
