<!DOCTYPE verb SYSTEM "verb.dtd">
<verb>
    <id> 争做 </id>
    <frameset id="f1">
        <role argnum="0" argrole="agent"/>
        <role argnum="1" argrole=""/>
        <frame>
            <mapping>
                <V/>
                <mapitem src="sbj" trg="arg0"/>
            </mapping>
            <example>
                <parse>
                    所有 的 互联网 企业 都 在 #争做# 二流 企业 ， 一个是 人流 ， 一个 是 现金流 ， 其实 我 理解 人流 又 包括 两 层 具体 含义 ， 一个 是 客户 的 人流 ， 一个 是 企业 人才 的 人 流 
                </parse>
                <arg n="0">
                    所有 的 互联网 企业
                </arg>
                <arg n="1">二流 企业</arg>
                <V/>
            </example>
        </frame>
    </frameset>
    <frameset id="f2">
        <role argnum="0" argrole="agent"/>
        <role argnum="1" argrole="theme"/>
        <frame>
            <mapping>
                <V/>
                <mapitem src="sbj" trg="arg0"/>
            </mapping>
            <example>
                <parse>
                    谢篱 没有 再 去 和 常 会 #争做# 家务 ， 而 是 来到 窗 前 ， 扶 着 窗棂 锻炼 ， 这 是 她 每 天 必 做 的 事情 
                </parse>
                <arg n="0">
                    谢篱
                </arg>
                <arg n="1">家务</arg>
                <V/>
            </example>
        </frame>
    </frameset>
</verb>
