<!DOCTYPE verb SYSTEM "verb.dtd">
<verb>
    <id> 坏死 </id>
    <frameset id="f1">
        <role argnum="0" argrole="theme"/>
        <frame>
            <mapping>
                <V/>
                <mapitem src="sbj" trg="arg0"/>
            </mapping>
            <example>
                <parse>
                    当晚 ， 黄女士 被 送到 福田 医院 后 ， 经 医生 诊断 ， 黄 女士 右 前额 颅内 出血 ， 脑 肿胀 ， 部分 脑 组织 #坏死# 
                </parse>
                <arg n="0">
                    部分 脑 组织
                </arg>
                <V/>
            </example>
        </frame>
    </frameset>
</verb>
