<!DOCTYPE verb SYSTEM "verb.dtd">
<verb>
    <id> 失时 </id>
    <frameset id="f1">
        <role argnum="0" argrole="agent"/>
        <frame>
            <mapping>
                <V/>
                <mapitem src="sbj" trg="arg0"/>
            </mapping>
            <example>
                <parse>
                    君子 #失时# ， 拱手于 小人 之下
                </parse>
                <arg n="0">
                    君子
                </arg>
                <V/>
            </example>
        </frame>
    </frameset>
</verb>
