<!DOCTYPE verb SYSTEM "verb.dtd">
<verb>
    <id> 失笑 </id>
    <frameset id="f1">
        <role argnum="0" argrole="agent"/>
        <frame>
            <mapping>
                <V/>
                <mapitem src="sbj" trg="arg0"/>
            </mapping>
            <example>
                <parse>
                    大 了 以后 ， 想起 这 事 ， 我 总是 #失笑# 
                </parse>
                <arg n="0">
                    我 
                </arg>
                <V/>
            </example>
        </frame>
    </frameset>
</verb>
