<!DOCTYPE verb SYSTEM "verb.dtd">
<verb>
    <id> 狡辩 </id>
    <frameset id="f1">
        <role argnum="0" argrole="agent"/>
        <frame>
            <mapping>
                <V/>
                <mapitem src="sbj" trg="arg0"/>
            </mapping>
            <example>
                <parse>
                    ( (IP (IP (ADVP (AD 那么))
                    (NP-PN-TPC (NR 小泉))
                    (FLR (SP 呢))
                    (PU ，)
                    (NP-SBJ (PN 他))
                    (VP (ADVP (AD 也))
                    (VP (VC 是)
                    (VP (VP (VV 表示))
                    (PU ，)
                    (VP (ADVP (AD 就是说))
                    (PU ，)
                    (FLR (IJ 呃))
                    (PU ，)
                    (PP-BNF (P 给)
                    (NP (PN 自己)))
                    (VP (VV 狡辩)))))))
                    (PU ，)
                    (IP (FLR (IJ 啊))
                    (PU ，)
                    (NP-SBJ (PN 他))
                    (VP (VV 说)
                    (FLR (SP 呢))
                    (PU ，)
                    (IP-OBJ (FLR (IJ 呃))
                    (PU ，)
                    (FLR (PN 这个))
                    (IP-SBJ (NP-SBJ (PN 他))
                    (VP (VV 去)
                    (VP (VV 参拜))))
                    (VP (ADVP (AD 并不))
                    (VP (VC 是)
                    (IP-PRD (NP-SBJ (-NONE- *pro*))
                    (VP (VV 美化)
                    (NP-OBJ (NN 战争)))))))))
                    (PU 。)))
                </parse>
                <arg n="m" f="DIS">那么</arg>
                <arg n="0">小泉 他  </arg>
                <arg n="m" f="ADV">也 </arg>
                <arg n="m" f="DIS"> 就是说 </arg>
                <arg n="m" f="BNF"> 给自己 </arg>
                <V/>
            </example>
        </frame>
    </frameset>
</verb>
