<!DOCTYPE verb SYSTEM "verb.dtd">
<verb>
    <id> 挂失 </id>
    <frameset id="f1">
        <role argnum="0" argrole="agent"/>
        <role argnum="1" argrole="theme"/>
        <role argnum="2" argrole="receipient"/>
        <frame>
            <mapping>
                <V/>
                <mapitem src="sbj" trg="arg0"/>
            </mapping>
            <example>
                <parse>
                    这时 我 就 确定 被 偷 了 我 赶紧 电话 #挂失# 信用卡 提款卡 ， 在 挂失 的 过程 中 与 服务 人员 讨论 怎 会 发生 这 种 事 ， 由于 柜子 完好 无 伤 ， 因此 我 开始 都 没 想到 可能 是 被 偷 了
                </parse>
                <arg n="0">
                    我
                </arg>
                <arg n="1">信用卡 提款卡</arg>
                <V/>
            </example>
            <example>
                <parse>
                    任 先生 先后 到 多 家 银行 #挂失# 
                </parse>
                <arg n="0">
                    任 先生
                </arg>
                <arg n="2">多 家 银行</arg>
                <V/>
            </example>
        </frame>
    </frameset>
    <frameset id="f2">
        <role argnum="0" argrole="entity with the property"/>
        <frame>
            <mapping>
                <V/>
                <mapitem src="sbj" trg="arg0"/>
            </mapping>
            <example>
                <parse>
                    彩票 不 记名 不 #挂失# ， 不 返还 本金 ， 不 流通 使用 
                </parse>
                <arg n="0">
                    彩票
                </arg>
                <V/>
            </example>
        </frame>
    </frameset>
</verb>
