<!DOCTYPE verb SYSTEM "verb.dtd">
<verb>
    <id> 探问 </id>
    <frameset id="f1">
        <role argnum="0" argrole="agent"/>
        <role argnum="1" argrole="theme"/>
        <role argnum="2" argrole="receipient"/>
        <role argnum="3" argrole="content"/>
        <frame>
            <mapping>
                <V/>
                <mapitem src="sbj" trg="arg0"/>
            </mapping>
            <example>
                <parse>
                    在 大陆 经商 的 张学良 的 侄女 张闾蘅 和 时任 全 国 政协 副秘书长 的 杨虎城 之 子 杨拯民 ， 到 解放军 总 医院 看望 吕正操 ， 才 把 张学良 夫妇 赴 美 探亲 的 事情 告诉 了 吕正操 ， 并 #探问# 吕正操 对 此 事 有 何 打算 
                </parse>
                <arg n="0">
                    在 大陆 经商 的 张学良 的 侄女 张闾蘅 和 时任 全 国 政协 副秘书长 的 杨虎城 之 子 杨拯民
                </arg>
                <arg n="2">吕正操 </arg>
                <arg n="3">对 此 事 有 何 打算</arg>
                <V/>
            </example>
            <example>
                <parse>
                    当 那 顶 白色 的 顶蓬 再度 撑起 ， 人们 纷纷 涌到 下面 ， #探问# 缘由 
                </parse>
                <arg n="0">
                    人们
                </arg>
                <arg n="1">缘由</arg>
                <V/>
            </example>
            <example>
                <parse>
                    严密 的 监控 ， 电话 查勤 ， 向 你 的 朋友 #探问# 你 的 行踪 ， 他 连 你 的 人 你 的 灵魂 都 要 一清二楚 决 不 能 忍受 与 你 相处 时 也许 你 心 里 还 想 着 别人 
                </parse>
                <arg n="1">
                    你 的 行踪 
                </arg>
                <arg n="2">你 的 朋友</arg>
                <V/>
            </example>
        </frame>
    </frameset>
</verb>
