<!DOCTYPE verb SYSTEM "verb.dtd">
<verb>
    <id> 畏缩 </id>
    <frameset id="f1">
        <role argnum="0" argrole="agent"/>
        <frame>
            <mapping>
                <V/>
                <mapitem src="sbj" trg="arg0"/>
            </mapping>
            <example>
                <parse>
                    洪峰 一脸 的 疲惫 ， 象个 做 了 错事 的 孩子 ， 而 又 毫 无 争辨 的 理由 ， 尴尬 地 #畏缩# 在 妈妈 身边 ， 灰头土脸 地 等候 发落 
                </parse>
                <arg n="0">
                    洪峰
                </arg>
                <V/>
            </example>
        </frame>
    </frameset>
    <frameset id="f2">
        <role argnum="0" argrole="entity with the property"/>
        <frame>
            <mapping>
                <V/>
                <mapitem src="sbj" trg="arg0"/>
            </mapping>
            <example>
                <parse>
                    您 好 我 家 男孩 五 岁 半， 在 熟悉 的 环境 中 学习 感悟 能力 较 好 ， 和 同龄人 的 交往 也 大方 ， 但 在 陌生 环境 中 特别 #畏缩# ， 且 易 受惊 ， 譬如 害怕 看 电影 ， 老师 批评 别 的 小 朋友 他 也 会 害怕 
                </parse>
                <arg n="0">
                    我 家 男孩
                </arg>
                <V/>
            </example>
        </frame>
    </frameset>
</verb>
