<!DOCTYPE verb SYSTEM "verb.dtd">
<verb>
    <id> 瞑目 </id>
    <frameset id="f1">
        <role argnum="0" argrole="agent"/>
        <frame>
            <mapping>
                <V/>
                <mapitem src="sbj" trg="arg0"/>
            </mapping>
            <example>
                <parse>
                    她 在 爱人 的 怀抱 中 #瞑目# 
                </parse>
                <arg n="0">
                    她
                </arg>
                <V/>
            </example>
        </frame>
    </frameset>
</verb>
