<!DOCTYPE verb SYSTEM "verb.dtd">
<verb>
    <id> 窨 </id>
    <frameset id="f1">
        <role argnum="0" argrole="agent"/>
        <role argnum="1" argrole="theme"/>
        <frame>
            <mapping>
                <V/>
                <mapitem src="sbj" trg="arg0"/>
            </mapping>
            <example>
                <parse>
                    玫瑰 花 采下 后 ， 经 适当 摊放 ， 折瓣 ， 拣 去 花蒂 花蕊 ， 以 净花 瓣 #窨# 茶
                </parse>
                <arg n="1">
                    茶
                </arg>
                <V/>
            </example>
        </frame>
    </frameset>
</verb>
