<!DOCTYPE verb SYSTEM "verb.dtd">
<verb>
    <id> 筑巢 </id>
    <frameset id="f1">
        <role argnum="0" argrole="agent"/>
        <role argnum="1" argrole="locative"/>
        <frame>
            <mapping>
                <V/>
                <mapitem src="sbj" trg="arg0"/>
            </mapping>
            <example>
                <parse>
                    如果 燕子 在 燕屋 横梁 上 #筑巢# ， 燕 盏 会 成 船形 
                </parse>
                <arg n="0">
                    燕子
                </arg>
                <arg n="1">燕屋 横梁 上</arg>
                <V/>
            </example>
        </frame>
    </frameset>
    <frameset id="f2">
        <role argnum="0" argrole="agent"/>
        <role argnum="1" argrole="locative"/>
        <frame>
            <mapping>
                <V/>
                <mapitem src="sbj" trg="arg0"/>
            </mapping>
            <example>
                <parse>
                    南宁 分行 越南 西贡 商信 银行 南宁 代表处 南洋 商业 银行 南宁 分行 等 金凤 凰 纷纷 #筑巢# 广西 首府 南宁 
                </parse>
                <arg n="0">
                    南宁 分行 越南 西贡 商信 银行 南宁 代表处 南洋 商业 银行 南宁 分行 等 金凤 凰
                </arg>
                <arg n="1">广西 首府 南宁 </arg>
                <V/>
            </example>
        </frame>
    </frameset>
</verb>
