<!DOCTYPE verb SYSTEM "verb.dtd">
<verb>
    <id> 简慢 </id>
    <frameset id="f1">
        <role argnum="0" argrole="agent"/>
        <role argnum="1" argrole="theme"/>
        <frame>
            <mapping>
                <V/>
                <mapitem src="sbj" trg="arg0"/>
            </mapping>
            <example>
                <parse>
                    犬子 有失 教养 , #简慢# 了 大人 ,万请 海涵
                </parse>
                <arg n="0">
                    犬子
                </arg>
                <arg n="1">大人</arg>
                <V/>
            </example>
        </frame>
    </frameset>
</verb>
