<!DOCTYPE verb SYSTEM "verb.dtd">
<verb>
    <id> 听天由命 </id>
    <frameset id="f1">
        <role argnum="0" argrole="agent who leaves everything to fate"/>
        <frame>
            <mapping>
                <V/>
                <mapitem src="sbj" trg="arg0"/>
            </mapping>
            <example>
                <parse>
                    ( (IP (IP-IMP (NP-SBJ (-NONE- *pro*)) 
                    (VP (VP (ADVP (AD 不要))
                    (VP (VA 愤怒)))
                    (PU ，)
                    (VP (ADVP (AD 甚至))
                    (VP (ADVP (AD 不要))
                    (VP (VV 抱怨))))))
                    (PU ，)
                    (IP (PP-DIR (P 面对)
                    (NP (CP (WHNP-1 (-NONE- *OP*)) 
                    (CP (IP (PU “)
                    (NP-SBJ (-NONE- *pro*)) 
                    (VP (ADVP (AD 无法))
                    (VP (VV 预报)
                    (NP-OBJ (-NONE- *T*-1))))
                    (PU ”))
                    (DEC 的)))
                    (NP (NN 地震))))
                    (PU ，)
                    (NP-SBJ (PN 我们))
                    (VP (ADVP (AD 只))
                    (VP (VV 能)
                    (VP (PP-LOC (P 在)
                    (LCP (NP (NN 绝望))
                    (LC 中)))
                    (VP (VV 听天由命))))))
                    (PU ！))) 
                </parse>
                <arg n="m" f="ADV">(PP-DIR (P 面对)
                    (NP (CP (WHNP-1 (-NONE- *OP*)) 
                    (CP (IP (PU “)
                    (NP-SBJ (-NONE- *pro*)) 
                    (VP (ADVP (AD 无法))
                    (VP (VV 预报)
                    (NP-OBJ (-NONE- *T*-1))))
                    (PU ”))
                    (DEC 的)))
                    (NP (NN 地震))))
                </arg>
                <arg n="0">我们</arg>
                <arg n="m" f="ADV">只</arg>
                <arg n="m" f="LOC">(PP-LOC (P 在)
                    (LCP (NP (NN 绝望))
                    (LC 中)))
                </arg>
                <V/>
            </example>
        </frame>
    </frameset>
</verb>
