<!DOCTYPE verb SYSTEM "verb.dtd">
<verb>
    <id> 玩儿 </id>
    <frameset id="f1">
        <role argnum="0" argrole="game player"/>
        <role argnum="1" argrole="game"/>
        <frame>
            <mapping>
                <V/>
                <mapitem src="sbj" trg="arg0"/>
                <mapitem src="npobj" trg="arg1"/>
            </mapping>
            <example>
                <parse>
                    ( (IP-Q (NP-SBJ (-NONE- *pro*))
                    (VP (VP (VV 玩儿)
                    (NP-OBJ (NN 游戏)))
                    (VP (ADVP (AD 也))
                    (VP (VV 能)
                    (VP (VV 发财)))))
                    (PU ？))) 
                    
                </parse>
                <arg n="0">
                    *pro*
                </arg>
                <arg n="1">
                    游戏
                </arg>
                <V/>
            </example>
        </frame>
    </frameset>
</verb>
