<!DOCTYPE verb SYSTEM "verb.dtd">
<verb>
    <id> 颓废 </id>
    <frameset id="f1">
        <role argnum="0" argrole="entity that is decadent"/>
        <frame>
            <mapping>
                <V/>
                <mapitem src="sbj" trg="arg0"/>
            </mapping>
            <example>
                <parse>
                    ( (IP (IP (NP-PN (NR 布努埃尔))
                    (VP (VV 展现)
                    (AS 了)
                    (NP-OBJ (QP (CD 一)
                    (CLP (M 种)))
                    (DNP (NP (ADJP (JJ 激进)
                    (CC 和)
                    (JJ 反传统))
                    (NP (NN 宗教)))
                    (DEG 的))
                    (NP (NN 世界观)))))
                    (PU ，)
                    (IP (NP-SBJ (PN 他))
                    (VP (VV 认为)
                    (CP-OBJ (IP (PP-LOC (P 在)
                    (LCP (NP (DP (DT 这个))
                    (NP (NN 世界)))
                    (LC 上)))
                    (NP-SBJ (NN 社会))
                    (VP (VC 是)
                    (VP (VP (VA 颓废))
                    (CC 和)
                    (VP (PP (P 与)
                    (NP (NN 人类)
                    (NN 解放)))
                    (VP (VV 对立))))))
                    (SP 的))))
                    (PU 。))) 
                    
                </parse>
                <arg n="m" f="LOC">
                    在这个世界上
                </arg>
                <arg n="0">
                    社会
                </arg>
                <V/>
            </example>
        </frame>
    </frameset>
</verb>
