<!DOCTYPE verb SYSTEM "verb.dtd">
<verb>
    <id> 笑到 </id>
    <frameset id="f1">
        <role argnum="0" argrole="laugher"/>
        <role argnum="1" argrole="time or location that Arg0 keeps laughing till"/>
        <frame>
            <mapping>
                <V/>
                <mapitem src="sbj" trg="arg0"/>
            </mapping>
            <example>
                <parse>
                    ( (IP (ADVP (AD 这样))
                    (PU ，)
                    (NP-SBJ (PN 你))
                    (VP (ADVP (AD 才))
                    (VP (VV 能)
                    (VP (VV 笑到)
                    (NP-TMP (NT 最后)))))
                    (PU 。))) 
                    
                </parse>
                <arg n="m" f="ADV">
                    这样
                </arg>
                <arg n="0">
                    你
                </arg>
                <arg n="m" f="DIS">
                    才
                </arg>
                <arg n="1">
                    最后
                </arg>
                <V/>
            </example>
        </frame>
    </frameset>
</verb>
