<!DOCTYPE verb SYSTEM "verb.dtd">
<verb>
    <id> 公之于众 </id>
    <frameset id="f1">
        <role argnum="0" argrole="agent who announce Arg1 to the public"/>
        <role argnum="1" argrole="information being announced"/>
        <frame>
            <mapping>
                <V/>
                <mapitem src="sbj" trg="arg0"/>
            </mapping>
            <example>
                <parse>
                    ( (IP (NP-TMP (NT 今天))
                    (NP-SBJ (NP-PN (NR 上海)
                    (NN 公交卡)
                    (NN 公司))
                    (CC 与)
                    (NP (NP-APP (PN 其)
                    (NN 行业)
                    (NN 主管)
                    (NN 部门))
                    (NP-PN (NR 上海市)
                    (NN 建设)
                    (NN 交通委))))
                    (PU ，)
                    (VP (VP (PP-ADV (P 就)
                    (NP (NN 公交卡)
                    (NN 押金)
                    (NN 事件)))
                    (VP (ADVP (AD 正式))
                    (VP (VV 表态))))
                    (PU ，)
                    (VP (ADVP (AD 将))
                    (PP-DIR (P 对)
                    (NP (NN 公交卡)
                    (NN 押金)
                    (NN 问题)))
                    (VP (VV 进行)
                    (NP-OBJ (NN 审计))))
                    (PU ，)
                    (VP (ADVP (AD 同时))
                    (VP (VV 会)
                    (VP (BA 将)
                    (IP-OBJ (NP-SBJ (NN 审计)
                    (NN 结果))
                    (VP (VV 公之于众)))))))
                    (PU 。))) 
                    
                </parse>
                <arg n="m" f="TMP">
                    今天
                </arg>
                <arg n="0">
                    上海公交卡公司
                </arg>
                <arg n="m" f="DIS">
                    同时
                </arg>
                <arg n="1">
                    审计结果
                </arg>
                <V/>
            </example>
        </frame>
    </frameset>
</verb>
