<!DOCTYPE verb SYSTEM "verb.dtd">
<verb>
    <id> 到货 </id>
    <frameset id="f1">
        <role argnum="0" argrole="the merchandise"/>
        <role argnum="1" argrole="the destination of arg0"/>
        <frame>
            <mapping>
                <V/>
                <mapitem src="sbj" trg="arg0"/>
            </mapping>
            <example>
                <parse>
                    索泰 是 此 举 的 顶力 支持者 ， 发布 了 众多 绿色版 显卡 ， 近日 上海 又 #到货# 了 一款 索 泰 的 米格版
                </parse>
                <arg n="0">
                    一款 索 泰 的 米格版
                </arg>
                <arg n="1">上海</arg>
                <V/>
            </example>
        </frame>
        <frame>
            <mapping>
                <V/>
                <mapitem src="sbj" trg="arg0"/>
            </mapping>
            <example>
                <parse>
                    近日 富士 最 新 发布 的 数码 相机 富士 4905 正式 #到货# 广州 太平洋 卖场
                </parse>
                <arg n="0">
                    富士 最 新 发布 的 数码 相机 富士 4905
                </arg>
                <arg n="1">广州 太平洋 卖场</arg>
                <V/>
            </example>
        </frame>
    </frameset>
</verb>
