<!DOCTYPE verb SYSTEM "verb.dtd">
<verb>
    <id> 丧身 </id>
    <frameset id="f1">
        <role argnum="0" argrole="agent"/>
        <role argnum="1" argrole="locative"/>
        <frame>
            <mapping>
                <V/>
                <mapitem src="sbj" trg="arg0"/>
            </mapping>
            <example>
                <parse>
                    麦克阿瑟 动用 多 架 飞机 袭击 该 舰队 ， 日军 陆战队 队员 大都 #丧身# 鱼腹 ， 部队 给养 军需 用品 弹药 全部 沉入 大海 ， 莱城 和 萨拉莫阿 轻取 而 胜
                </parse>
                <arg n="0">
                    日军 陆战队 队员
                </arg>
                <arg n="1">鱼腹</arg>
                <V/>
            </example>
        </frame>
    </frameset>
</verb>
