<!DOCTYPE verb SYSTEM "verb.dtd">
<verb>
    <id> 包饭 </id>
    <frameset id="f1">
        <role argnum="0" argrole="agent"/>
        <frame>
            <mapping>
                <V/>
                <mapitem src="sbj" trg="arg0"/>
            </mapping>
            <example>
                <parse>
                    中午 单位 不 #包饭# ， 我 就 自 带盒饭 用 微波炉 热来 吃 ， 结果 年内 我 就 把 自己 养胖 了
                </parse>
                <arg n="0">
                    单位
                </arg>
                <V/>
            </example>
        </frame>
    </frameset>
</verb>
