<!DOCTYPE verb SYSTEM "verb.dtd">
<verb>
    <id> 匿迹 </id>
    <frameset id="f1">
        <role argnum="0" argrole="agent"/>
        <role argnum="1" argrole="entity disappearing"/>
        <role argnum="2" argrole="locative"/>
        <frame>
            <mapping>
                <V/>
                <mapitem src="sbj" trg="arg0"/>
            </mapping>
            <example>
                <parse>
                    此刻 已 是 晨曦 初露 ， 赵青 冷静 地 将 妻子 的 遗体 背到 村 外 深井 ， 沉尸 #匿迹#
                </parse>
                <arg n="0">
                    赵青
                </arg>
                <V/>
            </example>
        </frame>
        <frame>
            <mapping>
                <V/>
                <mapitem src="sbj" trg="arg0"/>
            </mapping>
            <example>
                <parse>
                    此前 ， 恒 天然 授权 三鹿 经营 安满 安怡 ， 经历 了 三聚 氰胺 事件 ， 两 大 品牌 一度 在 中国 市场 #匿迹#
                </parse>
                <arg n="1">
                    两 大 品牌
                </arg>
                <arg n="2">中国 市场</arg>
                <V/>
            </example>
        </frame>
    </frameset>
</verb>
