<!DOCTYPE verb SYSTEM "verb.dtd">
<verb>
    <id> 匡正 </id>
    <frameset id="f1">
        <role argnum="0" argrole="agent"/>
        <role argnum="1" argrole="theme"/>
        <frame>
            <mapping>
                <V/>
                <mapitem src="sbj" trg="arg0"/>
            </mapping>
            <example>
                <parse>
                    孔子 说 君子 ， 饮食 不 求 饱足 ， 居住 不 要求 舒适 ， 对 工作 勤劳 敏捷 ， 说话 却 小心 谨慎 ， 到 有 道 的 人 那里 去 #匡正# 自己 ， 这样 可以 说 是 好 学 了
                </parse>
                <arg n="0">
                    君子
                </arg>
                <arg n="1">自己</arg>
                <V/>
            </example>
        </frame>
    </frameset>
</verb>
