<!DOCTYPE verb SYSTEM "verb.dtd">
<verb>
    <id> 升入 </id>
    <frameset id="f1">
        <role argnum="0" argrole="entity undergoing rising"/>
        <role argnum="1" argrole="locative, source"/>
        <role argnum="2" argrole="locative, destination"/>
        <frame>
            <mapping>
                <V/>
                <mapitem src="sbj" trg="arg0"/>
            </mapping>
            <example>
                <parse>
                    小 女 从 小学 #升入# 初中 时 ， 上海 已经 取消 了 小升 初 统 考 
                </parse>
                <arg n="0">
                    小 女
                </arg>
                <arg n="1">小学</arg>
                <arg n="2">初中</arg>
                <V/>
            </example>
        </frame>
    </frameset>
</verb>
