<!DOCTYPE verb SYSTEM "verb.dtd">
<verb>
    <id> 压价 </id>
    <frameset id="f1">
        <role argnum="0" argrole="agent"/>
        <role argnum="1" argrole="party opposite arg0"/>
        <role argnum="2" argrole="the merchandise"/>
        <frame>
            <mapping>
                <V/>
                <mapitem src="sbj" trg="arg0"/>
            </mapping>
            <example>
                <parse>
                    守 着 这 个 下家 ， 他 一边 向 山西 唐家 兄弟 #压价# ， 反正 银子 也 是 黑来 的, 一边则 对 江苏 苏北 李某 抬价
                </parse>
                <arg n="0">
                    他
                </arg>
                <arg n="1">山西 唐家 兄弟</arg>
                <V/>
            </example>
        </frame>
        <frame>
            <mapping>
                <V/>
                <mapitem src="sbj" trg="arg0"/>
            </mapping>
            <example>
                <parse>
                    受 全球 经济 大幅 波动 影响 ， 富士康 大量 变相 裁员 ， 对 洗衣 服务 也 不断 #压价# ， 导致 成立 以来 每 年 保持 以上 x% 增长 的 现代 后勤 今年 出现 了 业绩 波动
                </parse>
                <arg n="0">
                    富士康
                </arg>
                <arg n="2">洗衣 服务</arg>
                <V/>
            </example>
        </frame>
    </frameset>
</verb>
