<!DOCTYPE verb SYSTEM "verb.dtd">
<verb>
    <id> 濡染 </id>
    <frameset id="f1">
        <role argnum="0" argrole="patient"/>
        <role argnum="1" argrole="theme"/>
        <frame>
            <mapping>
                <V/>
                <mapitem src="sbj" trg="arg0"/>
            </mapping>
            <example>
                <parse>
                    明清 客家 移民 和 湖广 填 四川 ， 使 巴蜀 大地 再次 #濡染# 了 源自 中原 又 蕴涵 典型 的 中南华南 东南 沿海 地域 特色 的 多 种 形态 的 文化
                </parse>
                <arg n="0">
                    巴蜀 大地
                </arg>
                <arg n="1">源自 中原 又 蕴涵 典型 的 中南华南 东南 沿海 地域 特色 的 多 种 形态 的 文化</arg>
                <V/>
            </example>
        </frame>
    </frameset>
</verb>
