<!DOCTYPE verb SYSTEM "verb.dtd">
<verb>
    <id> 狂奔 </id>
    <frameset id="f1">
        <role argnum="0" argrole="agent"/>
        <frame>
            <mapping>
                <V/>
                <mapitem src="sbj" trg="arg0"/>
            </mapping>
            <example>
                <parse>
                    赤脚 侠 #狂奔# 拿下 歹徒
                </parse>
                <arg n="0">
                    赤脚 侠
                </arg>
                <V/>
            </example>
        </frame>
    </frameset>
</verb>
