<?xml version="1.0" encoding="UTF-8" standalone="no"?>

<!DOCTYPE inventory SYSTEM "inventory.dtd">

<inventory lemma="dAr-u-v">
    <commentary></commentary>
    
    <sense group="1" n="1" name="to go around, circulate" type=""><commentary>
            
        </commentary>
        <examples>فِي بَعْضِ المُؤَسَّساتِ، حَمَلَ الرُّؤَساءُ وَ
            
            المُدِيرُونَ العَرِيضَةَ وَ دارُوا عَلَى المُوَظَّفِينَ
            
            لِلتَوْقِيعِ.
        </examples>
        
        <mappings>
            <wn version="1.7"></wn><omega></omega><pb></pb>
        </mappings>
        
        <SENSE_META clarity=""></SENSE_META>
    </sense>
    
    <sense group="1" n="2" name="to happen, take place" type=""><commentary>
            
        </commentary>
        <examples>وَ قَد دارَ نِقاشٌ حَوْلَ هُوِيَّةِ الصُّنْدُوقِ
            
            الوَطَنِيِّ لِلضَمانِ الاِجْتِماعِيِّ.
        </examples>
        <mappings>
            
            <wn version="1.7"></wn><omega></omega><pb></pb>
            
        </mappings>
        <SENSE_META clarity=""></SENSE_META>
    </sense>
    
    <sense group="1" n="3" name="to revolve, rotate" type="">
        
        <commentary></commentary>
        
        <examples>وَ إِن يَكُنْ الصَّمْتُ يُكَتِّمُ الأَفْواهَ فِي هذِهِ الهَيْئاتِ
            
            البَشَرِيَّةِ ، فَإِنَّ الدَّرْوِيشَ الَّذِي يَدُورُ عَلَى نَفْسِهِ فِي
            
            حَرَكَةٍ آلِيَّةٍ يُوقِظُ فِينا شُعُوراً بِلا نِهايَةِ الحَرَكَةِ.
        </examples>
        
        <mappings>
            <wn version="1.7"></wn><omega></omega>
            
            <pb></pb>
        </mappings>
        <SENSE_META clarity=""></SENSE_META>
    </sense>
    
<sense group="1" n="4" name="none of the above" type="">
  <commentary>
Automatically generated NOTA sense (bbn)
  </commentary>
  <examples>
  </examples>
  <mappings>
    <wn version="2.1"></wn>
    <omega></omega><pb></pb>
    <fn></fn>
  </mappings><SENSE_META clarity=""/>
</sense>
    <WORD_META authors="Vicky" sample_score="-"></WORD_META>
    

<ita count="0" ann_1_2_agreement="0.0" />
</inventory>

