<?xml version="1.0" encoding="utf-8" standalone="yes"?>
<!DOCTYPE inventory SYSTEM "inventory.dtd">

<inventory lemma="Tariyqap-n">
    
    <commentary>
        
    </commentary>
    
    <sense n="1" type="" name="Way, manner, style" group="1">
        
        <commentary>
            
        </commentary>
        
        <examples>
            
            رتبت كتبي بطريقة معينة
            
            I arrange my books in a specific manner.
            
            اقص شعر راسي بطريقة معينة
            
            I have my hair cut in a certain style.
            
            طريقتك في كتابة الورقة العلمية غريبة
            
            Your style of writing scientific papers is strange.
            
        </examples>
        
        <mappings>
            
            <wn version="0"></wn>
            
            <omega></omega>
            
            <pb></pb>
            
        </mappings>
        <SENSE_META clarity=""/>
        
    </sense>
    
    
    <sense n="2" type="" name= "Approach, method" group="1">
        
        <commentary> Plural
            
        </commentary>
        
        <examples>
            
            إن آليكس يستخدم طريقة في بحثه تختلف عن الطلاب الاخرين
            
            Alex uses a different approach in his research than that of other students.
            
            إن الطريقة التي تستخدم لمعالجة الشرائح المرضية في هذا المختبر جديدة
            
            The method used to process the pathology slides in this lab is new.
            
            لقد تم اكتشاف طرق جديدة  لتشخيص مرضى السرطان
            
            New approaches have been discovered to diagnose cancer patients.
            
            إن طريقة التجربة هي مجموع الخطوات لعمل التجربة
            
            The experimental method is the steps by which an experiment is performed.
            
        </examples>
        
        <mappings>
            
            <wn version="0"></wn>
            
            <omega></omega>
            
            <pb></pb>
            
        </mappings>
        <SENSE_META clarity=""/>
        
    </sense>
    
    <sense n="3" type="" name= "Process" group="1">
        
        <commentary>
            
        </commentary>
        
        <examples>
            
            إن طريقة عمل الكيك ليست صعبة
            
            The process of cake making is not difficult.
            
            إن الطريقة التي تعمل بها تلك الآلة تعتمد على الطاقة الشمسية
            
            The process by which this machine works depends on solar energy.
            
            إن تعليب الطعام يتم بطريقة معينة
            
            Food canning is achieved by a certain process.
            
        </examples>
        
        <mappings>
            
            <wn version="0"></wn>
            
            <omega></omega>
            
            <pb></pb>
            
        </mappings>
        <SENSE_META clarity=""/>
        
    </sense>
    
    <sense n="4" type="" name= "Creed, school of thought أفكار عملية وفلسفية" group="1">
        
        <commentary> Plural
            
        </commentary>
        
        <examples>
            
            إن الطوائف الأسلامية المختلفة لها طرق مستمدة من علماء الدين
            
            Islamic sects are different schools of thought that stem from the particular imam who founded them.
            
            هناك طرق صوفية مختلفة ومتنوعة
            
            There are different and diverse Sufi philosophies.
            
        </examples>
        
        <mappings>
            
            <wn version="0"></wn>
            
            <omega></omega>
            
            <pb></pb>
            
        </mappings>
        <SENSE_META clarity=""/>
        
    </sense>
    
<sense group="1" n="5" name="none of the above" type="">
  <commentary>
Automatically generated NOTA sense (bbn)
  </commentary>
  <examples>
  </examples>
  <mappings>
    <wn version="2.1"></wn>
    <omega></omega><pb></pb>
    <fn></fn>
  </mappings><SENSE_META clarity=""/>
</sense>
    <WORD_META authors="Mamon Hatmal, Bonnie Stalls" sample_score=""/>
    
    

<ita count="0" ann_1_2_agreement="0.0" />
</inventory>



